.gitignore
MANIFEST.in
README.rst
setup.cfg
setup.py
Products/__init__.py
Products.PloneboardSubscription.egg-info/PKG-INFO
Products.PloneboardSubscription.egg-info/SOURCES.txt
Products.PloneboardSubscription.egg-info/dependency_links.txt
Products.PloneboardSubscription.egg-info/entry_points.txt
Products.PloneboardSubscription.egg-info/namespace_packages.txt
Products.PloneboardSubscription.egg-info/not-zip-safe
Products.PloneboardSubscription.egg-info/requires.txt
Products.PloneboardSubscription.egg-info/top_level.txt
Products/PloneboardSubscription/NotificationTool.py
Products/PloneboardSubscription/README.txt
Products/PloneboardSubscription/__init__.py
Products/PloneboardSubscription/config.py
Products/PloneboardSubscription/configure.zcml
Products/PloneboardSubscription/doi18ndude
Products/PloneboardSubscription/interfaces.py
Products/PloneboardSubscription/tool.gif
Products/PloneboardSubscription/version.txt
Products/PloneboardSubscription/Extensions/__init__.py
Products/PloneboardSubscription/Extensions/migrations.py
Products/PloneboardSubscription/browser/__init__.py
Products/PloneboardSubscription/browser/configure.zcml
Products/PloneboardSubscription/browser/events.py
Products/PloneboardSubscription/browser/subscribe.pt
Products/PloneboardSubscription/browser/views.py
Products/PloneboardSubscription/locales/PloneboardSubscription.pot
Products/PloneboardSubscription/locales/de/LC_MESSAGES/PloneboardSubscription.po
Products/PloneboardSubscription/locales/en/LC_MESSAGES/PloneboardSubscription.po
Products/PloneboardSubscription/locales/en/LC_MESSAGES/README.txt
Products/PloneboardSubscription/locales/fr/LC_MESSAGES/PloneboardSubscription.po
Products/PloneboardSubscription/locales/fr/LC_MESSAGES/README.txt
Products/PloneboardSubscription/profiles/default/toolset.xml
Products/PloneboardSubscription/tests/CheckHtmlFormat.txt
Products/PloneboardSubscription/tests/CheckMailTemplate.txt
Products/PloneboardSubscription/tests/MemberSubscribesToConv.txt
Products/PloneboardSubscription/tests/MemberSubscribesToForum.txt
Products/PloneboardSubscription/tests/PloneboardSubscriptionTC.py
Products/PloneboardSubscription/tests/__init__.py
Products/PloneboardSubscription/tests/testFunctional.py
docs/CREDITS.txt
docs/HISTORY.txt
docs/INSTALL.txt
docs/LICENSE.GPL
docs/LICENSE.txt