Metadata-Version: 1.1
Name: Products.PloneboardSubscription
Version: 0.9
Summary: Enables email subscription to Ploneboard posts
Home-page: http://plone.org/products/products.ploneboardsubscription
Author: Suresh V
Author-email: suresh@grafware.com
License: GPL
Platform: UNKNOWN
Classifier: Framework :: Plone
Classifier: Programming Language :: Python
